odoo/addons/hr_timesheet_task_stage/README.rst
odoo/addons/hr_timesheet_task_stage/__init__.py
odoo/addons/hr_timesheet_task_stage/__manifest__.py
odoo/addons/hr_timesheet_task_stage/i18n/de.po
odoo/addons/hr_timesheet_task_stage/i18n/es.po
odoo/addons/hr_timesheet_task_stage/i18n/fr.po
odoo/addons/hr_timesheet_task_stage/i18n/he_IL.po
odoo/addons/hr_timesheet_task_stage/i18n/hr_timesheet_task_stage.pot
odoo/addons/hr_timesheet_task_stage/i18n/it.po
odoo/addons/hr_timesheet_task_stage/i18n/pt_BR.po
odoo/addons/hr_timesheet_task_stage/i18n/sv.po
odoo/addons/hr_timesheet_task_stage/models/__init__.py
odoo/addons/hr_timesheet_task_stage/models/account_analytic_line.py
odoo/addons/hr_timesheet_task_stage/readme/CONTRIBUTORS.md
odoo/addons/hr_timesheet_task_stage/readme/DESCRIPTION.md
odoo/addons/hr_timesheet_task_stage/static/description/icon.png
odoo/addons/hr_timesheet_task_stage/static/description/index.html
odoo/addons/hr_timesheet_task_stage/tests/__init__.py
odoo/addons/hr_timesheet_task_stage/tests/test_hr_timesheet_task_stage.py
odoo/addons/hr_timesheet_task_stage/views/account_analytic_line.xml
odoo_addon_hr_timesheet_task_stage-19.0.1.0.0.2.dist-info/METADATA
odoo_addon_hr_timesheet_task_stage-19.0.1.0.0.2.dist-info/WHEEL
odoo_addon_hr_timesheet_task_stage-19.0.1.0.0.2.dist-info/top_level.txt
odoo_addon_hr_timesheet_task_stage-19.0.1.0.0.2.dist-info/RECORD
