Metadata-Version: 2.1
Name: odoo-addon-hr_timesheet_task_stage
Version: 19.0.1.0.0.2
Requires-Dist: odoo==19.0.*
Summary: Open/Close task from corresponding Task Log entry
Home-page: https://github.com/OCA/timesheet
License: AGPL-3
Author: Tecnativa, CorporateHub, Odoo Community Association (OCA)
Author-email: support@odoo-community.org
Classifier: Programming Language :: Python
Classifier: Framework :: Odoo
Classifier: Framework :: Odoo :: 19.0
Classifier: License :: OSI Approved :: GNU Affero General Public License v3
